kakaocert/__init__.py
kakaocert/kakaocertService.py
kakaocert-2.52.0.dist-info/LICENSE.md
kakaocert-2.52.0.dist-info/METADATA
kakaocert-2.52.0.dist-info/WHEEL
kakaocert-2.52.0.dist-info/top_level.txt
kakaocert-2.52.0.dist-info/RECORD
