Metadata-Version: 2.1
Name: kakaocert
Version: 2.52.0
Summary: kakaocert API SDK Library
Home-page: https://github.com/linkhub-sdk/kakaocert.py
Author: Jeong Yohan
Author-email: code@linkhubcorp.com
License: MIT
Download-URL: https://github.com/linkhub-sdk/kakaocert.py/archive/2.52.0.tar.gz
Platform: Posix; MacOS X; Windows
Classifier: Development Status :: 5 - Production/Stable
Classifier: Intended Audience :: Developers
Classifier: License :: OSI Approved :: MIT License
Classifier: Operating System :: OS Independent
Classifier: Topic :: Internet
Classifier: Programming Language :: Python :: 2
Classifier: Programming Language :: Python :: 2.6
Classifier: Programming Language :: Python :: 2.7
Classifier: Programming Language :: Python :: 3
Classifier: Programming Language :: Python :: 3.3
Classifier: Programming Language :: Python :: 3.4
Classifier: Programming Language :: Python :: 3.5
Classifier: Programming Language :: Python :: 3.6
Classifier: Programming Language :: Python :: 3.7
Requires-Dist: linkhub
